axxac/__init__.py
axxac/auto_case.py
axxac/generate_case_list.py
axxac/generate_itest_json.py
axxac/itest_template.json
axxac/main.py
axxac/path_tool.py
axxac/read_case_config.py
axxac/read_require_config.py
axxac/require.py
axxac-1.2.1.dist-info/LICENSE
axxac-1.2.1.dist-info/METADATA
axxac-1.2.1.dist-info/WHEEL
axxac-1.2.1.dist-info/entry_points.txt
axxac-1.2.1.dist-info/top_level.txt
axxac-1.2.1.dist-info/RECORD
