Metadata-Version: 2.1
Name: axxac
Version: 1.2.1
Summary: Generate case list and itest json automatically.
Home-page: https://github.com/bjwuzh/autocase.git
Author: bjwuzh
Author-email: bjwuzh@163.com
License: MIT
Platform: UNKNOWN
Requires-Dist: xlwt
Requires-Dist: xlrd
